<rdf:RDF xmlns:dc="http://purl.org/dc/elements/1.1/" xmlns:dcterms="http://purl.org/dc/terms/" xmlns:edm="http://www.europeana.eu/schemas/edm/" xmlns:nave="http://schemas.delving.eu/nave/terms/" xmlns:ore="http://www.openarchives.org/ore/terms/" xmlns:rdf="http://www.w3.org/1999/02/22-rdf-syntax-ns#"><edm:ProvidedCHO rdf:about="http://data.collectienederland.nl/resource/document/catharijneconvent/ABM-v65c"><dc:type>kacheltegel</dc:type><dcterms:medium>aardewerk</dcterms:medium><dc:creator>onbekend</dc:creator><dcterms:extent> hoogte 17.0 cm</dcterms:extent><dc:coverage>Duitsland</dc:coverage><dc:identifier>ABM v65c</dc:identifier><dc:title>Kacheltegel met Prudentia</dc:title><dc:type>reliëf</dc:type><dcterms:extent> breedte 17.0 cm</dcterms:extent><dc:type>tegel</dc:type><dcterms:medium>glazuur</dcterms:medium><dc:date>1590 - 1599</dc:date><dcterms:extent> diepte 3.0 cm</dcterms:extent><dcterms:created>1590 - 1599</dcterms:created></edm:ProvidedCHO><ore:Aggregation rdf:about="http://data.collectienederland.nl/resource/aggregation/catharijneconvent/ABM-v65c"><edm:object rdf:resource="https://adlib.catharijneconvent.nl/wwwopacximages/wwwopac.ashx?command=getcontent&amp;server=images&amp;value=ABM%20v65a_2.jpg"/><edm:dataProvider>Museum Catharijneconvent</edm:dataProvider><edm:isShownAt rdf:resource="https://adlib.catharijneconvent.nl/Details/collect/11620"/><edm:isShownBy rdf:resource="https://adlib.catharijneconvent.nl/wwwopacximages/wwwopac.ashx?command=getcontent&amp;server=images&amp;value=ABM%20v65a_2.jpg"/><edm:isShownBy rdf:resource="https://adlib.catharijneconvent.nl/wwwopacximages/wwwopac.ashx?command=getcontent&amp;server=images&amp;value=ABM%20v65c_1.jpg"/><edm:object rdf:resource="https://adlib.catharijneconvent.nl/wwwopacximages/wwwopac.ashx?command=getcontent&amp;server=images&amp;value=ABM%20v65c_1.jpg"/><edm:aggregatedCHO rdf:resource="http://data.collectienederland.nl/resource/document/catharijneconvent/ABM-v65c"/></ore:Aggregation></rdf:RDF>