<rdf:RDF xmlns:dc="http://purl.org/dc/elements/1.1/" xmlns:dcterms="http://purl.org/dc/terms/" xmlns:edm="http://www.europeana.eu/schemas/edm/" xmlns:nave="http://schemas.delving.eu/nave/terms/" xmlns:ore="http://www.openarchives.org/ore/terms/" xmlns:rdf="http://www.w3.org/1999/02/22-rdf-syntax-ns#"><edm:ProvidedCHO rdf:about="http://data.collectienederland.nl/resource/document/catharijneconvent/RMCC-f128"><dc:title>Portret van pastoor Grimmelt en kapelaan</dc:title><dcterms:extent> hoogte 14.9 cm</dcterms:extent><dc:identifier>RMCC f128</dc:identifier><dcterms:created>1880 - 1909</dcterms:created><dc:type>foto</dc:type><dcterms:extent> breedte 10.4 cm</dcterms:extent><dcterms:medium>karton</dcterms:medium><dc:creator>onbekend</dc:creator><dcterms:medium>fotopapier</dcterms:medium><dc:date>1880 - 1909</dc:date></edm:ProvidedCHO><ore:Aggregation rdf:about="http://data.collectienederland.nl/resource/aggregation/catharijneconvent/RMCC-f128"><edm:isShownAt rdf:resource="https://adlib.catharijneconvent.nl/Details/collect/28046"/><edm:aggregatedCHO rdf:resource="http://data.collectienederland.nl/resource/document/catharijneconvent/RMCC-f128"/><edm:dataProvider>Museum Catharijneconvent</edm:dataProvider><edm:object rdf:resource="https://adlib.catharijneconvent.nl/wwwopacximages/wwwopac.ashx?command=getcontent&amp;server=images&amp;value=RMCC%20f128_1.jpg"/><edm:isShownBy rdf:resource="https://adlib.catharijneconvent.nl/wwwopacximages/wwwopac.ashx?command=getcontent&amp;server=images&amp;value=RMCC%20f128_1.jpg"/></ore:Aggregation></rdf:RDF>