<rdf:RDF xmlns:dc="http://purl.org/dc/elements/1.1/" xmlns:dcterms="http://purl.org/dc/terms/" xmlns:edm="http://www.europeana.eu/schemas/edm/" xmlns:nave="http://schemas.delving.eu/nave/terms/" xmlns:ore="http://www.openarchives.org/ore/terms/" xmlns:rdf="http://www.w3.org/1999/02/22-rdf-syntax-ns#"><edm:ProvidedCHO rdf:about="http://data.collectienederland.nl/resource/document/catharijneconvent/BMH-t10266a"><dcterms:created>1954 - 1964</dcterms:created><dcterms:extent> hoogte 56.0 cm</dcterms:extent><dc:date>1954 - 1964</dc:date><dcterms:extent> breedte 148.0 cm</dcterms:extent><dc:identifier>BMH t10266a</dc:identifier><dcterms:medium>katoen</dcterms:medium><dc:creator>onbekend</dc:creator><dc:title>Kleding kindsheid, rood jasje met grijze bies van een hoofdman over tot slaaf gemaakten</dc:title><dc:coverage>Nederland</dc:coverage><dc:type>processiegoed</dc:type></edm:ProvidedCHO><ore:Aggregation rdf:about="http://data.collectienederland.nl/resource/aggregation/catharijneconvent/BMH-t10266a"><edm:isShownBy rdf:resource="https://adlib.catharijneconvent.nl/wwwopacximages/wwwopac.ashx?command=getcontent&amp;server=images&amp;value=BMH%20t10266a_1.JPG"/><edm:isShownAt rdf:resource="https://adlib.catharijneconvent.nl/Details/collect/22192"/><edm:isShownBy rdf:resource="https://adlib.catharijneconvent.nl/wwwopacximages/wwwopac.ashx?command=getcontent&amp;server=images&amp;value=BMH%20t10266a_2.JPG"/><edm:object rdf:resource="https://adlib.catharijneconvent.nl/wwwopacximages/wwwopac.ashx?command=getcontent&amp;server=images&amp;value=BMH%20t10266a_2.JPG"/><edm:aggregatedCHO rdf:resource="http://data.collectienederland.nl/resource/document/catharijneconvent/BMH-t10266a"/><edm:dataProvider>Museum Catharijneconvent</edm:dataProvider><edm:object rdf:resource="https://adlib.catharijneconvent.nl/wwwopacximages/wwwopac.ashx?command=getcontent&amp;server=images&amp;value=BMH%20t10266a_1.JPG"/></ore:Aggregation></rdf:RDF>