<rdf:RDF xmlns:dc="http://purl.org/dc/elements/1.1/" xmlns:dcterms="http://purl.org/dc/terms/" xmlns:edm="http://www.europeana.eu/schemas/edm/" xmlns:nave="http://schemas.delving.eu/nave/terms/" xmlns:ore="http://www.openarchives.org/ore/terms/" xmlns:rdf="http://www.w3.org/1999/02/22-rdf-syntax-ns#"><edm:ProvidedCHO rdf:about="http://data.collectienederland.nl/resource/document/catharijneconvent/SPKK-v162.66"><dc:creator>Callenbach</dc:creator><dcterms:medium>linnen</dcterms:medium><dc:coverage>Nijkerk</dc:coverage><dc:date>1908</dc:date><dcterms:created>1908</dcterms:created><dcterms:medium>papier</dcterms:medium><dc:type>schoolplaat</dc:type><dcterms:extent> breedte 65.0 cm</dcterms:extent><dc:title>Bijbelplaat Oude Testament 5: David voert de arke Gods op naar Jeruzalem</dc:title><dcterms:extent> hoogte 90.0 cm</dcterms:extent><dc:type>bijbelplaat</dc:type><dc:identifier>SPKK v162.66</dc:identifier></edm:ProvidedCHO><ore:Aggregation rdf:about="http://data.collectienederland.nl/resource/aggregation/catharijneconvent/SPKK-v162.66"><edm:dataProvider>Museum Catharijneconvent</edm:dataProvider><edm:isShownAt rdf:resource="https://adlib.catharijneconvent.nl/Details/collect/40315"/><edm:aggregatedCHO rdf:resource="http://data.collectienederland.nl/resource/document/catharijneconvent/SPKK-v162.66"/></ore:Aggregation></rdf:RDF>