<rdf:RDF xmlns:dc="http://purl.org/dc/elements/1.1/" xmlns:dcterms="http://purl.org/dc/terms/" xmlns:edm="http://www.europeana.eu/schemas/edm/" xmlns:nave="http://schemas.delving.eu/nave/terms/" xmlns:ore="http://www.openarchives.org/ore/terms/" xmlns:rdf="http://www.w3.org/1999/02/22-rdf-syntax-ns#"><edm:ProvidedCHO rdf:about="http://data.collectienederland.nl/resource/document/catharijneconvent/ABM-t2451b"><dcterms:created>1890 - 1899</dcterms:created><dcterms:extent> hoogte 47.5 cm</dcterms:extent><dcterms:extent> breedte 49.0 cm</dcterms:extent><dcterms:medium>linnendamast</dcterms:medium><dc:type>corporale</dc:type><dc:type>liturgica</dc:type><dc:identifier>ABM t2451b</dc:identifier><dc:creator>onbekend</dc:creator><dc:date>1890 - 1899</dc:date><dc:title>Witte corporale met ingeweven rankenrand waartussen lijdenswerktuigen en tekst</dc:title></edm:ProvidedCHO><ore:Aggregation rdf:about="http://data.collectienederland.nl/resource/aggregation/catharijneconvent/ABM-t2451b"><edm:aggregatedCHO rdf:resource="http://data.collectienederland.nl/resource/document/catharijneconvent/ABM-t2451b"/><edm:isShownAt rdf:resource="https://adlib.catharijneconvent.nl/Details/collect/39286"/><edm:dataProvider>Museum Catharijneconvent</edm:dataProvider></ore:Aggregation></rdf:RDF>