<rdf:RDF xmlns:dc="http://purl.org/dc/elements/1.1/" xmlns:dcterms="http://purl.org/dc/terms/" xmlns:edm="http://www.europeana.eu/schemas/edm/" xmlns:nave="http://schemas.delving.eu/nave/terms/" xmlns:ore="http://www.openarchives.org/ore/terms/" xmlns:rdf="http://www.w3.org/1999/02/22-rdf-syntax-ns#"><ore:Aggregation rdf:about="http://data.collectienederland.nl/resource/aggregation/catharijneconvent/ABM-f112"><edm:isShownBy rdf:resource="https://adlib.catharijneconvent.nl/wwwopacximages/wwwopac.ashx?command=getcontent&amp;server=images&amp;value=ABM%20f112_1.jpg"/><edm:isShownAt rdf:resource="https://adlib.catharijneconvent.nl/Details/collect/41422"/><edm:object rdf:resource="https://adlib.catharijneconvent.nl/wwwopacximages/wwwopac.ashx?command=getcontent&amp;server=images&amp;value=ABM%20f112_1.jpg"/><edm:aggregatedCHO rdf:resource="http://data.collectienederland.nl/resource/document/catharijneconvent/ABM-f112"/><edm:dataProvider>Museum Catharijneconvent</edm:dataProvider></ore:Aggregation><edm:ProvidedCHO rdf:about="http://data.collectienederland.nl/resource/document/catharijneconvent/ABM-f112"><dc:title>Kruisbeeld, door G.B. Brom (hoog 66 cm)</dc:title><dc:identifier>ABM f112</dc:identifier><dc:type>foto</dc:type><dcterms:extent> breedte 10.7 cm</dcterms:extent><dc:creator>Winsen, J.J.A. van</dc:creator><dcterms:medium>fotopapier</dcterms:medium><dcterms:medium>karton</dcterms:medium><dc:date>1875 - 1899</dc:date><dcterms:created>1875 - 1899</dcterms:created><dcterms:extent> hoogte 16.7 cm</dcterms:extent></edm:ProvidedCHO></rdf:RDF>