<rdf:RDF xmlns:dc="http://purl.org/dc/elements/1.1/" xmlns:dcterms="http://purl.org/dc/terms/" xmlns:edm="http://www.europeana.eu/schemas/edm/" xmlns:nave="http://schemas.delving.eu/nave/terms/" xmlns:ore="http://www.openarchives.org/ore/terms/" xmlns:rdf="http://www.w3.org/1999/02/22-rdf-syntax-ns#"><edm:ProvidedCHO rdf:about="http://data.collectienederland.nl/resource/document/catharijneconvent/RMCC-te54"><dcterms:extent> breedte 58.5 cm</dcterms:extent><dcterms:created>1895 - 1904</dcterms:created><dc:identifier>RMCC te54</dc:identifier><dcterms:medium>papier</dcterms:medium><dcterms:medium>calqueerpapier</dcterms:medium><dc:date>1895 - 1904</dc:date><dc:type>pentekening</dc:type><dcterms:extent> hoogte 42.5 cm</dcterms:extent><dc:type>tekening</dc:type><dc:creator>Cuypers, Pierre Joseph Hubert</dc:creator><dc:title>Altaar fragment linkerzijde (Roermond, kapel in het Zand)</dc:title></edm:ProvidedCHO><ore:Aggregation rdf:about="http://data.collectienederland.nl/resource/aggregation/catharijneconvent/RMCC-te54"><edm:isShownBy rdf:resource="https://adlib.catharijneconvent.nl/wwwopacximages/wwwopac.ashx?command=getcontent&amp;server=images&amp;value=RMCC%20te54_1.JPG"/><edm:dataProvider>Museum Catharijneconvent</edm:dataProvider><edm:aggregatedCHO rdf:resource="http://data.collectienederland.nl/resource/document/catharijneconvent/RMCC-te54"/><edm:isShownAt rdf:resource="https://adlib.catharijneconvent.nl/Details/collect/32386"/><edm:object rdf:resource="https://adlib.catharijneconvent.nl/wwwopacximages/wwwopac.ashx?command=getcontent&amp;server=images&amp;value=RMCC%20te54_1.JPG"/></ore:Aggregation></rdf:RDF>