<rdf:RDF xmlns:dc="http://purl.org/dc/elements/1.1/" xmlns:dcterms="http://purl.org/dc/terms/" xmlns:edm="http://www.europeana.eu/schemas/edm/" xmlns:nave="http://schemas.delving.eu/nave/terms/" xmlns:ore="http://www.openarchives.org/ore/terms/" xmlns:rdf="http://www.w3.org/1999/02/22-rdf-syntax-ns#"><ore:Aggregation rdf:about="http://data.collectienederland.nl/resource/aggregation/catharijneconvent/RMCC-v630.23"><edm:aggregatedCHO rdf:resource="http://data.collectienederland.nl/resource/document/catharijneconvent/RMCC-v630.23"/><edm:isShownBy rdf:resource="https://adlib.catharijneconvent.nl/wwwopacximages/wwwopac.ashx?command=getcontent&amp;server=images&amp;value=RMCC%20v630.23_1.jpg"/><edm:dataProvider>Museum Catharijneconvent</edm:dataProvider><edm:isShownAt rdf:resource="https://adlib.catharijneconvent.nl/Details/collect/33921"/><edm:object rdf:resource="https://adlib.catharijneconvent.nl/wwwopacximages/wwwopac.ashx?command=getcontent&amp;server=images&amp;value=RMCC%20v630.23_1.jpg"/></ore:Aggregation><edm:ProvidedCHO rdf:about="http://data.collectienederland.nl/resource/document/catharijneconvent/RMCC-v630.23"><dc:coverage>Lisse</dc:coverage><dcterms:extent> hoogte 30.8 cm</dcterms:extent><dc:type>grammofoonplaat</dc:type><dcterms:created>1979</dcterms:created><dc:creator>Gouden Harpen</dc:creator><dcterms:extent> breedte 31.0 cm</dcterms:extent><dc:date>1979</dc:date><dcterms:medium>kunststof</dcterms:medium><dc:title>Korenaren uit de volle oogst, meditatieserie, nr. 31: ds. M.B. van de Akker, ds. P. Roos</dc:title><dc:identifier>RMCC v630.23</dc:identifier><dcterms:medium>karton</dcterms:medium></edm:ProvidedCHO></rdf:RDF>