<rdf:RDF xmlns:dc="http://purl.org/dc/elements/1.1/" xmlns:dcterms="http://purl.org/dc/terms/" xmlns:edm="http://www.europeana.eu/schemas/edm/" xmlns:nave="http://schemas.delving.eu/nave/terms/" xmlns:ore="http://www.openarchives.org/ore/terms/" xmlns:rdf="http://www.w3.org/1999/02/22-rdf-syntax-ns#"><edm:ProvidedCHO rdf:about="http://data.collectienederland.nl/resource/document/catharijneconvent/SPKK-g80"><dc:creator>Kon. Drukkerijen Lankhout-Immig</dc:creator><dc:type>document</dc:type><dc:type>prent</dc:type><dcterms:extent> breedte 24.5 cm</dcterms:extent><dc:coverage>Den Haag</dc:coverage><dcterms:created>1950 - 1959</dcterms:created><dc:title>Prent t.g.a. de afgelegde geloofsbelijdenis en bevestiging als lidmaat der N.H. Kerk</dc:title><dcterms:extent> hoogte 32.0 cm</dcterms:extent><dc:type>getuigschrift</dc:type><dcterms:medium>papier</dcterms:medium><dc:identifier>SPKK g80</dc:identifier><dc:date>1950 - 1959</dc:date></edm:ProvidedCHO><ore:Aggregation rdf:about="http://data.collectienederland.nl/resource/aggregation/catharijneconvent/SPKK-g80"><edm:dataProvider>Museum Catharijneconvent</edm:dataProvider><edm:aggregatedCHO rdf:resource="http://data.collectienederland.nl/resource/document/catharijneconvent/SPKK-g80"/><edm:isShownAt rdf:resource="https://adlib.catharijneconvent.nl/Details/collect/34294"/><edm:isShownBy rdf:resource="https://adlib.catharijneconvent.nl/wwwopacximages/wwwopac.ashx?command=getcontent&amp;server=images&amp;value=SPKK%20g80_1.jpg"/><edm:object rdf:resource="https://adlib.catharijneconvent.nl/wwwopacximages/wwwopac.ashx?command=getcontent&amp;server=images&amp;value=SPKK%20g80_1.jpg"/></ore:Aggregation></rdf:RDF>