<rdf:RDF xmlns:dc="http://purl.org/dc/elements/1.1/" xmlns:dcterms="http://purl.org/dc/terms/" xmlns:edm="http://www.europeana.eu/schemas/edm/" xmlns:nave="http://schemas.delving.eu/nave/terms/" xmlns:ore="http://www.openarchives.org/ore/terms/" xmlns:rdf="http://www.w3.org/1999/02/22-rdf-syntax-ns#"><edm:ProvidedCHO rdf:about="http://data.collectienederland.nl/resource/document/catharijneconvent/RMCC-v276b"><dc:identifier>RMCC v276b</dc:identifier><dc:date>1980 - 1989</dc:date><dc:title>Wenslepeltje met "Gods zegen gewenst"</dc:title><dc:creator>H.C.U.</dc:creator><dcterms:extent> hoogte 11.8 cm</dcterms:extent><dcterms:extent> diepte 1.3 cm</dcterms:extent><dcterms:medium>zilver</dcterms:medium><dc:type>evangelisatiemateriaal</dc:type><dcterms:created>1980 - 1989</dcterms:created><dcterms:extent> breedte 2.3 cm</dcterms:extent><dc:type>lepel</dc:type><dcterms:medium>metaal</dcterms:medium></edm:ProvidedCHO><ore:Aggregation rdf:about="http://data.collectienederland.nl/resource/aggregation/catharijneconvent/RMCC-v276b"><edm:aggregatedCHO rdf:resource="http://data.collectienederland.nl/resource/document/catharijneconvent/RMCC-v276b"/><edm:isShownAt rdf:resource="https://adlib.catharijneconvent.nl/Details/collect/33214"/><edm:isShownBy rdf:resource="https://adlib.catharijneconvent.nl/wwwopacximages/wwwopac.ashx?command=getcontent&amp;server=images&amp;value=RMCC%20v276b_1.JPG"/><edm:dataProvider>Museum Catharijneconvent</edm:dataProvider><edm:object rdf:resource="https://adlib.catharijneconvent.nl/wwwopacximages/wwwopac.ashx?command=getcontent&amp;server=images&amp;value=RMCC%20v276b_1.JPG"/><edm:object rdf:resource="https://adlib.catharijneconvent.nl/wwwopacximages/wwwopac.ashx?command=getcontent&amp;server=images&amp;value=RMCC%20v276b_2.JPG"/><edm:isShownBy rdf:resource="https://adlib.catharijneconvent.nl/wwwopacximages/wwwopac.ashx?command=getcontent&amp;server=images&amp;value=RMCC%20v276b_2.JPG"/></ore:Aggregation></rdf:RDF>