<rdf:RDF xmlns:dc="http://purl.org/dc/elements/1.1/" xmlns:dcterms="http://purl.org/dc/terms/" xmlns:edm="http://www.europeana.eu/schemas/edm/" xmlns:nave="http://schemas.delving.eu/nave/terms/" xmlns:ore="http://www.openarchives.org/ore/terms/" xmlns:rdf="http://www.w3.org/1999/02/22-rdf-syntax-ns#"><ore:Aggregation rdf:about="http://data.collectienederland.nl/resource/aggregation/catharijneconvent/RMCC-te9.361"><edm:isShownBy rdf:resource="https://adlib.catharijneconvent.nl/wwwopacximages/wwwopac.ashx?command=getcontent&amp;server=images&amp;value=RMCC%20te9.361_1.JPG"/><edm:aggregatedCHO rdf:resource="http://data.collectienederland.nl/resource/document/catharijneconvent/RMCC-te9.361"/><edm:isShownAt rdf:resource="https://adlib.catharijneconvent.nl/Details/collect/32200"/><edm:dataProvider>Museum Catharijneconvent</edm:dataProvider><edm:object rdf:resource="https://adlib.catharijneconvent.nl/wwwopacximages/wwwopac.ashx?command=getcontent&amp;server=images&amp;value=RMCC%20te9.361_1.JPG"/></ore:Aggregation><edm:ProvidedCHO rdf:about="http://data.collectienederland.nl/resource/document/catharijneconvent/RMCC-te9.361"><dcterms:medium>papier</dcterms:medium><dcterms:extent> hoogte 28.1 cm</dcterms:extent><dc:type>tekening</dc:type><dc:date>1939</dc:date><dc:title>Ontwerp vier glasramen met engelen (Beltrum, O.L. Vrouw ten Hemelopnemingkerk)</dc:title><dcterms:extent> breedte 64.5 cm</dcterms:extent><dc:creator>Kocken, Henricus Leonardus D.</dc:creator><dcterms:created>1939</dcterms:created><dc:identifier>RMCC te9.361</dc:identifier></edm:ProvidedCHO></rdf:RDF>