<rdf:RDF xmlns:dc="http://purl.org/dc/elements/1.1/" xmlns:dcterms="http://purl.org/dc/terms/" xmlns:edm="http://www.europeana.eu/schemas/edm/" xmlns:nave="http://schemas.delving.eu/nave/terms/" xmlns:ore="http://www.openarchives.org/ore/terms/" xmlns:rdf="http://www.w3.org/1999/02/22-rdf-syntax-ns#"><ore:Aggregation rdf:about="http://data.collectienederland.nl/resource/aggregation/catharijneconvent/StCC-m172"><edm:aggregatedCHO rdf:resource="http://data.collectienederland.nl/resource/document/catharijneconvent/StCC-m172"/><edm:object rdf:resource="https://adlib.catharijneconvent.nl/wwwopacximages/wwwopac.ashx?command=getcontent&amp;server=images&amp;value=StCC%20m172_2.jpg"/><edm:isShownAt rdf:resource="https://adlib.catharijneconvent.nl/Details/collect/69437"/><edm:isShownBy rdf:resource="https://adlib.catharijneconvent.nl/wwwopacximages/wwwopac.ashx?command=getcontent&amp;server=images&amp;value=StCC%20m172_1.jpg"/><edm:dataProvider>Museum Catharijneconvent</edm:dataProvider><edm:object rdf:resource="https://adlib.catharijneconvent.nl/wwwopacximages/wwwopac.ashx?command=getcontent&amp;server=images&amp;value=StCC%20m172_1.jpg"/><edm:isShownBy rdf:resource="https://adlib.catharijneconvent.nl/wwwopacximages/wwwopac.ashx?command=getcontent&amp;server=images&amp;value=StCC%20m172_2.jpg"/></ore:Aggregation><edm:ProvidedCHO rdf:about="http://data.collectienederland.nl/resource/document/catharijneconvent/StCC-m172"><dcterms:medium>koperlegering</dcterms:medium><dcterms:extent> hoogte 15.4 cm</dcterms:extent><dc:type>caravacakruis</dc:type><dc:creator>onbekend</dc:creator><dc:title>Caravacakruis met gekruisigde Christus en Maria en twee engeltjes aan de zijkant</dc:title><dc:identifier>StCC m172</dc:identifier><dc:date>1700 - 1899</dc:date><dc:type>devotionalia</dc:type><dc:coverage>Spanje</dc:coverage><dcterms:extent> breedte 9.0 cm</dcterms:extent><dcterms:created>1700 - 1899</dcterms:created></edm:ProvidedCHO></rdf:RDF>