<rdf:RDF xmlns:dc="http://purl.org/dc/elements/1.1/" xmlns:dcterms="http://purl.org/dc/terms/" xmlns:edm="http://www.europeana.eu/schemas/edm/" xmlns:nave="http://schemas.delving.eu/nave/terms/" xmlns:ore="http://www.openarchives.org/ore/terms/" xmlns:rdf="http://www.w3.org/1999/02/22-rdf-syntax-ns#"><edm:ProvidedCHO rdf:about="http://data.collectienederland.nl/resource/document/catharijneconvent/BMH-1308b"><dcterms:extent> diepte 8.0 cm</dcterms:extent><dc:date>1866</dc:date><dcterms:extent> breedte 36.0 cm</dcterms:extent><dc:creator>Janvier, Pierre-Désiré</dc:creator><dc:type>boek</dc:type><dc:identifier>BMH 1308b</dc:identifier><dc:creator>Bourassé, Jean-Jacques</dc:creator><dc:type>Bijbel</dc:type><dcterms:extent> hoogte 44.5 cm</dcterms:extent><dcterms:created>1866</dcterms:created><dc:coverage>Tours</dc:coverage><dcterms:medium>papier</dcterms:medium><dc:creator>Doré, Gustave</dc:creator><dc:title>La sainte bible : trad. nouvelle selon la Vulgate, Tome II</dc:title></edm:ProvidedCHO><ore:Aggregation rdf:about="http://data.collectienederland.nl/resource/aggregation/catharijneconvent/BMH-1308b"><edm:dataProvider>Museum Catharijneconvent</edm:dataProvider><edm:aggregatedCHO rdf:resource="http://data.collectienederland.nl/resource/document/catharijneconvent/BMH-1308b"/><edm:isShownAt rdf:resource="https://adlib.catharijneconvent.nl/Details/collect/70610"/></ore:Aggregation></rdf:RDF>