<rdf:RDF xmlns:dc="http://purl.org/dc/elements/1.1/" xmlns:dcterms="http://purl.org/dc/terms/" xmlns:edm="http://www.europeana.eu/schemas/edm/" xmlns:nave="http://schemas.delving.eu/nave/terms/" xmlns:ore="http://www.openarchives.org/ore/terms/" xmlns:rdf="http://www.w3.org/1999/02/22-rdf-syntax-ns#"><ore:Aggregation rdf:about="http://data.collectienederland.nl/resource/aggregation/catharijneconvent/BMH-odB.IV.10-2-"><edm:dataProvider>Museum Catharijneconvent</edm:dataProvider><edm:isShownAt rdf:resource="https://adlib.catharijneconvent.nl/Details/collect/62977"/><edm:aggregatedCHO rdf:resource="http://data.collectienederland.nl/resource/document/catharijneconvent/BMH-odB.IV.10-2-"/></ore:Aggregation><edm:ProvidedCHO rdf:about="http://data.collectienederland.nl/resource/document/catharijneconvent/BMH-odB.IV.10-2-"><dc:coverage>Keulen</dc:coverage><dc:date>1617</dc:date><dc:creator>Birckmann</dc:creator><dcterms:medium>papier</dcterms:medium><dc:creator>Mylius, Hermann</dc:creator><dcterms:created>1617</dcterms:created><dc:title>Brevis tractatus de sacramento poenitentiae, cum examine generali ad confessionem de tota vita, et, meditatione una pro communione. Ex Italico in latinum translatus</dc:title><dc:creator>Bruno, Vincentius</dc:creator><dc:type>boek</dc:type><dc:identifier>BMH odB.IV.10(2)</dc:identifier></edm:ProvidedCHO></rdf:RDF>