<rdf:RDF xmlns:dc="http://purl.org/dc/elements/1.1/" xmlns:dcterms="http://purl.org/dc/terms/" xmlns:edm="http://www.europeana.eu/schemas/edm/" xmlns:nave="http://schemas.delving.eu/nave/terms/" xmlns:ore="http://www.openarchives.org/ore/terms/" xmlns:rdf="http://www.w3.org/1999/02/22-rdf-syntax-ns#"><edm:ProvidedCHO rdf:about="http://data.collectienederland.nl/resource/document/catharijneconvent/BMH-odC.V.4-1-"><dcterms:extent> breedte 11.0 cm</dcterms:extent><dc:creator>Eilbracht, Philip</dc:creator><dc:date>1628</dc:date><dc:type>boek</dc:type><dcterms:extent> hoogte 16.5 cm</dcterms:extent><dc:identifier>BMH odC.V.4(1)</dc:identifier><dc:coverage>Keulen</dc:coverage><dc:title>Via compendiaria ad catholicam ecclesiam. Sive, Expedita et perspicua ratio ex intricatissimo sectarum hujus temporis labyrintho eluctandi et ad salutarem verae catholicae ecclesiae communionem accedendi [...]</dc:title><dc:creator>Grevenbruch, Gerhard</dc:creator><dcterms:extent> diepte 6.5 cm</dcterms:extent><dcterms:created>1628</dcterms:created><dcterms:medium>papier</dcterms:medium></edm:ProvidedCHO><ore:Aggregation rdf:about="http://data.collectienederland.nl/resource/aggregation/catharijneconvent/BMH-odC.V.4-1-"><edm:isShownAt rdf:resource="https://adlib.catharijneconvent.nl/Details/collect/68230"/><edm:aggregatedCHO rdf:resource="http://data.collectienederland.nl/resource/document/catharijneconvent/BMH-odC.V.4-1-"/><edm:dataProvider>Museum Catharijneconvent</edm:dataProvider></ore:Aggregation></rdf:RDF>