<rdf:RDF xmlns:dc="http://purl.org/dc/elements/1.1/" xmlns:dcterms="http://purl.org/dc/terms/" xmlns:edm="http://www.europeana.eu/schemas/edm/" xmlns:nave="http://schemas.delving.eu/nave/terms/" xmlns:ore="http://www.openarchives.org/ore/terms/" xmlns:rdf="http://www.w3.org/1999/02/22-rdf-syntax-ns#"><ore:Aggregation rdf:about="http://data.collectienederland.nl/resource/aggregation/catharijneconvent/BMH-Warm-pi1260A6-2-"><edm:isShownAt rdf:resource="https://adlib.catharijneconvent.nl/Details/collect/63721"/><edm:dataProvider>Museum Catharijneconvent</edm:dataProvider><edm:aggregatedCHO rdf:resource="http://data.collectienederland.nl/resource/document/catharijneconvent/BMH-Warm-pi1260A6-2-"/></ore:Aggregation><edm:ProvidedCHO rdf:about="http://data.collectienederland.nl/resource/document/catharijneconvent/BMH-Warm-pi1260A6-2-"><dc:identifier>BMH Warm pi1260A6(2)</dc:identifier><dc:coverage>Parijs</dc:coverage><dc:creator>Valla, Laurentius</dc:creator><dc:creator>Blaubloom, Louis</dc:creator><dc:creator>Colinaeus, Simon</dc:creator><dc:date>1530</dc:date><dc:title>De dialectica, libri III</dc:title><dcterms:medium>papier</dcterms:medium><dc:type>post-incunabel</dc:type><dcterms:created>1530</dcterms:created></edm:ProvidedCHO></rdf:RDF>