<rdf:RDF xmlns:dc="http://purl.org/dc/elements/1.1/" xmlns:dcterms="http://purl.org/dc/terms/" xmlns:edm="http://www.europeana.eu/schemas/edm/" xmlns:nave="http://schemas.delving.eu/nave/terms/" xmlns:ore="http://www.openarchives.org/ore/terms/" xmlns:rdf="http://www.w3.org/1999/02/22-rdf-syntax-ns#"><ore:Aggregation rdf:about="http://data.collectienederland.nl/resource/aggregation/catharijneconvent/ABM-p978"><edm:isShownBy rdf:resource="https://adlib.catharijneconvent.nl/wwwopacximages/wwwopac.ashx?command=getcontent&amp;server=images&amp;value=ABM%20p978_2.jpg"/><edm:dataProvider>Museum Catharijneconvent</edm:dataProvider><edm:aggregatedCHO rdf:resource="http://data.collectienederland.nl/resource/document/catharijneconvent/ABM-p978"/><edm:isShownAt rdf:resource="https://adlib.catharijneconvent.nl/Details/collect/7741"/><edm:object rdf:resource="https://adlib.catharijneconvent.nl/wwwopacximages/wwwopac.ashx?command=getcontent&amp;server=images&amp;value=ABM%20p978_1.jpg"/><edm:isShownBy rdf:resource="https://adlib.catharijneconvent.nl/wwwopacximages/wwwopac.ashx?command=getcontent&amp;server=images&amp;value=ABM%20p978_1.jpg"/><edm:object rdf:resource="https://adlib.catharijneconvent.nl/wwwopacximages/wwwopac.ashx?command=getcontent&amp;server=images&amp;value=ABM%20p978_2.jpg"/></ore:Aggregation><edm:ProvidedCHO rdf:about="http://data.collectienederland.nl/resource/document/catharijneconvent/ABM-p978"><dcterms:medium>zilver</dcterms:medium><dc:type>draagteken</dc:type><dc:identifier>ABM p978</dc:identifier><dc:type>draagpenning</dc:type><dcterms:extent> breedte 29.0 mm</dcterms:extent><dcterms:extent> hoogte 38.0 mm</dcterms:extent><dc:type>penning</dc:type><dcterms:created>1850 - 1949</dcterms:created><dc:title>Draagpenning, ovaal, Congregatie O.L.V. Onbevlekt Ontvangen van Goede Raad met Maria, kz. tekst</dc:title><dc:date>1850 - 1949</dc:date><dc:creator>onbekend</dc:creator></edm:ProvidedCHO></rdf:RDF>