<rdf:RDF xmlns:dc="http://purl.org/dc/elements/1.1/" xmlns:dcterms="http://purl.org/dc/terms/" xmlns:edm="http://www.europeana.eu/schemas/edm/" xmlns:nave="http://schemas.delving.eu/nave/terms/" xmlns:ore="http://www.openarchives.org/ore/terms/" xmlns:rdf="http://www.w3.org/1999/02/22-rdf-syntax-ns#"><edm:ProvidedCHO rdf:about="http://data.collectienederland.nl/resource/document/catharijneconvent/RMCC-t301"><dc:type>liturgica</dc:type><dcterms:medium>metaaldraad</dcterms:medium><dc:date>1960</dc:date><dc:coverage>Nijmegen</dc:coverage><dc:identifier>RMCC t301</dc:identifier><dc:title>Wit kazuifel geborduurd met stermotief, op achterzijde Heilige Familie</dc:title><dcterms:medium>gouddraad</dcterms:medium><dcterms:extent> hoogte 134.0 cm</dcterms:extent><dcterms:medium>wol</dcterms:medium><dcterms:medium>katoen</dcterms:medium><dc:type>kazuifel</dc:type><dc:creator>Stadelmaier, fa.</dc:creator><dcterms:medium>zijde</dcterms:medium><dcterms:created>1960</dcterms:created><dcterms:extent> breedte 149.5 cm</dcterms:extent></edm:ProvidedCHO><ore:Aggregation rdf:about="http://data.collectienederland.nl/resource/aggregation/catharijneconvent/RMCC-t301"><edm:object rdf:resource="https://adlib.catharijneconvent.nl/wwwopacximages/wwwopac.ashx?command=getcontent&amp;server=images&amp;value=RMCC%20t301_2.jpg"/><edm:isShownBy rdf:resource="https://adlib.catharijneconvent.nl/wwwopacximages/wwwopac.ashx?command=getcontent&amp;server=images&amp;value=RMCC%20t301_3.jpg"/><edm:isShownBy rdf:resource="https://adlib.catharijneconvent.nl/wwwopacximages/wwwopac.ashx?command=getcontent&amp;server=images&amp;value=RMCC%20t301_1.jpg"/><edm:isShownBy rdf:resource="https://adlib.catharijneconvent.nl/wwwopacximages/wwwopac.ashx?command=getcontent&amp;server=images&amp;value=RMCC%20t301_2.jpg"/><edm:aggregatedCHO rdf:resource="http://data.collectienederland.nl/resource/document/catharijneconvent/RMCC-t301"/><edm:object rdf:resource="https://adlib.catharijneconvent.nl/wwwopacximages/wwwopac.ashx?command=getcontent&amp;server=images&amp;value=RMCC%20t301_3.jpg"/><edm:dataProvider>Museum Catharijneconvent</edm:dataProvider><edm:object rdf:resource="https://adlib.catharijneconvent.nl/wwwopacximages/wwwopac.ashx?command=getcontent&amp;server=images&amp;value=RMCC%20t301_1.jpg"/><edm:isShownAt rdf:resource="https://adlib.catharijneconvent.nl/Details/collect/73411"/></ore:Aggregation></rdf:RDF>