<rdf:RDF xmlns:dc="http://purl.org/dc/elements/1.1/" xmlns:dcterms="http://purl.org/dc/terms/" xmlns:edm="http://www.europeana.eu/schemas/edm/" xmlns:nave="http://schemas.delving.eu/nave/terms/" xmlns:ore="http://www.openarchives.org/ore/terms/" xmlns:rdf="http://www.w3.org/1999/02/22-rdf-syntax-ns#"><edm:ProvidedCHO rdf:about="http://data.collectienederland.nl/resource/document/catharijneconvent/RMCC-od585c"><dcterms:medium>papier</dcterms:medium><dc:type>boek</dc:type><dc:identifier>RMCC od585c</dc:identifier><dc:creator>Saurin, Jacques</dc:creator><dc:coverage>Den Haag</dc:coverage><dc:creator>Hondt, Pieter de</dc:creator><dc:creator>Houbraken, Arnold</dc:creator><dc:creator>Hoet, Gerard (I)</dc:creator><dcterms:extent> breedte 34.0 cm</dcterms:extent><dc:date>1728</dc:date><dcterms:extent> diepte 4.5 cm</dcterms:extent><dcterms:extent> hoogte 47.0 cm</dcterms:extent><dcterms:created>1728</dcterms:created><dc:title>Taferelen der voornaamste geschiedenissen van het Oude en Nieuwe Testament [...] door [...] Hoet, Houbraken, en Picart getekent [...] en met beschrijvingen uitgebreid. Het derde deel.</dc:title><dc:creator>Picart, Bernard</dc:creator></edm:ProvidedCHO><ore:Aggregation rdf:about="http://data.collectienederland.nl/resource/aggregation/catharijneconvent/RMCC-od585c"><edm:object rdf:resource="https://adlib.catharijneconvent.nl/wwwopacximages/wwwopac.ashx?command=getcontent&amp;server=images&amp;value=RMCC%20od585a_2.jpg"/><edm:object rdf:resource="https://adlib.catharijneconvent.nl/wwwopacximages/wwwopac.ashx?command=getcontent&amp;server=images&amp;value=RMCC%20od585c,%20p.%201_1.jpg"/><edm:object rdf:resource="https://adlib.catharijneconvent.nl/wwwopacximages/wwwopac.ashx?command=getcontent&amp;server=images&amp;value=RMCC%20od585c,%20p.%2010_1.jpg"/><edm:isShownBy rdf:resource="https://adlib.catharijneconvent.nl/wwwopacximages/wwwopac.ashx?command=getcontent&amp;server=images&amp;value=RMCC%20od585c,%20tp_1.jpg"/><edm:isShownBy rdf:resource="https://adlib.catharijneconvent.nl/wwwopacximages/wwwopac.ashx?command=getcontent&amp;server=images&amp;value=RMCC%20od585c,%20p.%2010_1.jpg"/><edm:object rdf:resource="https://adlib.catharijneconvent.nl/wwwopacximages/wwwopac.ashx?command=getcontent&amp;server=images&amp;value=RMCC%20od585c,%20tp_1.jpg"/><edm:object rdf:resource="https://adlib.catharijneconvent.nl/wwwopacximages/wwwopac.ashx?command=getcontent&amp;server=images&amp;value=RMCC%20od585c,%20p.%20160_1.jpg"/><edm:dataProvider>Museum Catharijneconvent</edm:dataProvider><edm:isShownBy rdf:resource="https://adlib.catharijneconvent.nl/wwwopacximages/wwwopac.ashx?command=getcontent&amp;server=images&amp;value=RMCC%20od585c_1.jpg"/><edm:isShownBy rdf:resource="https://adlib.catharijneconvent.nl/wwwopacximages/wwwopac.ashx?command=getcontent&amp;server=images&amp;value=RMCC%20od585c,%20p.%20160_1.jpg"/><edm:isShownAt rdf:resource="https://adlib.catharijneconvent.nl/Details/collect/467164"/><edm:object rdf:resource="https://adlib.catharijneconvent.nl/wwwopacximages/wwwopac.ashx?command=getcontent&amp;server=images&amp;value=RMCC%20od585c_1.jpg"/><edm:aggregatedCHO rdf:resource="http://data.collectienederland.nl/resource/document/catharijneconvent/RMCC-od585c"/><edm:isShownBy rdf:resource="https://adlib.catharijneconvent.nl/wwwopacximages/wwwopac.ashx?command=getcontent&amp;server=images&amp;value=RMCC%20od585a_2.jpg"/><edm:isShownBy rdf:resource="https://adlib.catharijneconvent.nl/wwwopacximages/wwwopac.ashx?command=getcontent&amp;server=images&amp;value=RMCC%20od585c,%20p.%201_1.jpg"/></ore:Aggregation></rdf:RDF>