<rdf:RDF xmlns:dc="http://purl.org/dc/elements/1.1/" xmlns:dcterms="http://purl.org/dc/terms/" xmlns:edm="http://www.europeana.eu/schemas/edm/" xmlns:nave="http://schemas.delving.eu/nave/terms/" xmlns:ore="http://www.openarchives.org/ore/terms/" xmlns:rdf="http://www.w3.org/1999/02/22-rdf-syntax-ns#"><ore:Aggregation rdf:about="http://data.collectienederland.nl/resource/aggregation/catharijneconvent/ABM-t2527"><edm:dataProvider>Museum Catharijneconvent</edm:dataProvider><edm:isShownBy rdf:resource="https://adlib.catharijneconvent.nl/wwwopacximages/wwwopac.ashx?command=getcontent&amp;server=images&amp;value=ABM%20t2527_1.jpg"/><edm:object rdf:resource="https://adlib.catharijneconvent.nl/wwwopacximages/wwwopac.ashx?command=getcontent&amp;server=images&amp;value=ABM%20t2527_1.jpg"/><edm:aggregatedCHO rdf:resource="http://data.collectienederland.nl/resource/document/catharijneconvent/ABM-t2527"/><edm:isShownAt rdf:resource="https://adlib.catharijneconvent.nl/Details/collect/9863"/></ore:Aggregation><edm:ProvidedCHO rdf:about="http://data.collectienederland.nl/resource/document/catharijneconvent/ABM-t2527"><dcterms:extent> hoogte 39.5 cm</dcterms:extent><dcterms:created>1945</dcterms:created><dc:type>beurs</dc:type><dcterms:medium>zijde</dcterms:medium><dc:date>1945</dc:date><dc:creator>Brom-Fischer, Hildegard</dc:creator><dcterms:medium>goudleer</dcterms:medium><dc:type>liturgica</dc:type><dc:identifier>ABM t2527</dc:identifier><dcterms:medium>ripszijde</dcterms:medium><dc:title>Goudleren ziekenbeurs met phoenix, broden en vis, Lam Gods, pelikaan, waarin ABM m1619</dc:title><dc:type>ziekenbeurs</dc:type><dcterms:extent> breedte 43.5 cm</dcterms:extent></edm:ProvidedCHO></rdf:RDF>