<rdf:RDF xmlns:dc="http://purl.org/dc/elements/1.1/" xmlns:dcterms="http://purl.org/dc/terms/" xmlns:edm="http://www.europeana.eu/schemas/edm/" xmlns:nave="http://schemas.delving.eu/nave/terms/" xmlns:ore="http://www.openarchives.org/ore/terms/" xmlns:rdf="http://www.w3.org/1999/02/22-rdf-syntax-ns#"><edm:ProvidedCHO rdf:about="http://data.collectienederland.nl/resource/document/catharijneconvent/ABM-t2751t"><dc:type>fragment</dc:type><dc:title>Kleding buitengewoon kamerheer paus: strook veterkant hoort bij ABM t2751i</dc:title><dcterms:medium>katoen</dcterms:medium><dcterms:extent> hoogte 37.0 cm</dcterms:extent><dc:creator>onbekend</dc:creator><dc:date>1840 - 1849</dc:date><dcterms:extent> breedte 142.0 cm</dcterms:extent><dc:type>liturgica</dc:type><dc:identifier>ABM t2751t</dc:identifier><dcterms:created>1840 - 1849</dcterms:created><dc:type>superplie</dc:type></edm:ProvidedCHO><ore:Aggregation rdf:about="http://data.collectienederland.nl/resource/aggregation/catharijneconvent/ABM-t2751t"><edm:dataProvider>Museum Catharijneconvent</edm:dataProvider><edm:isShownAt rdf:resource="https://adlib.catharijneconvent.nl/Details/collect/10488"/><edm:aggregatedCHO rdf:resource="http://data.collectienederland.nl/resource/document/catharijneconvent/ABM-t2751t"/></ore:Aggregation></rdf:RDF>