<rdf:RDF xmlns:dc="http://purl.org/dc/elements/1.1/" xmlns:dcterms="http://purl.org/dc/terms/" xmlns:edm="http://www.europeana.eu/schemas/edm/" xmlns:nave="http://schemas.delving.eu/nave/terms/" xmlns:ore="http://www.openarchives.org/ore/terms/" xmlns:rdf="http://www.w3.org/1999/02/22-rdf-syntax-ns#"><edm:ProvidedCHO rdf:about="http://data.collectienederland.nl/resource/document/stedelijk-museum-schiedam/H-00002519.1-56"><dcterms:extent>diepte: 18,7 cm</dcterms:extent><dcterms:extent>doos 2 hoogte: 2,5 cm</dcterms:extent><dc:title>Het Grappige Vermenigvuldigings-Spel</dc:title><dcterms:provenance>Stedelijk Museum Schiedam</dcterms:provenance><dc:identifier>H-00002519.1-56</dc:identifier><dcterms:extent>diepte: 15,0 cm</dcterms:extent><dcterms:extent>breedte: 24,5 cm</dcterms:extent><dc:creator>Meinharde, R.</dc:creator><dcterms:created>1875 / 1900</dcterms:created><dc:date>1875 / 1900</dc:date><dcterms:extent>breedte: 15,0 cm</dcterms:extent><dcterms:extent>doos 1 hoogte: 2,6 cm</dcterms:extent><dc:type>spel</dc:type></edm:ProvidedCHO><ore:Aggregation rdf:about="http://data.collectienederland.nl/resource/aggregation/stedelijk-museum-schiedam/H-00002519.1-56"><edm:rights rdf:resource="https://rightsstatements.org/page/InC/1.0/"/><edm:object rdf:resource="https://api.stedelijkmuseumschiedam.nl/axiellweboai/wwwopac.ashx?command=getcontent&amp;server=images&amp;value=h-00002519.1.jpg"/><edm:isShownBy rdf:resource="https://api.stedelijkmuseumschiedam.nl/axiellweboai/wwwopac.ashx?command=getcontent&amp;server=images&amp;value=h-00002519.1.jpg"/><edm:provider>Rijksdienst voor het Cultureel Erfgoed</edm:provider><edm:aggregatedCHO rdf:resource="http://data.collectienederland.nl/resource/document/stedelijk-museum-schiedam/H-00002519.1-56"/><edm:dataProvider>Stedelijk Museum Schiedam</edm:dataProvider></ore:Aggregation></rdf:RDF>