<rdf:RDF xmlns:dc="http://purl.org/dc/elements/1.1/" xmlns:dcterms="http://purl.org/dc/terms/" xmlns:edm="http://www.europeana.eu/schemas/edm/" xmlns:nave="http://schemas.delving.eu/nave/terms/" xmlns:ore="http://www.openarchives.org/ore/terms/" xmlns:rdf="http://www.w3.org/1999/02/22-rdf-syntax-ns#"><ore:Aggregation rdf:about="http://data.collectienederland.nl/resource/aggregation/stedelijk-museum-schiedam/H-00002926"><edm:aggregatedCHO rdf:resource="http://data.collectienederland.nl/resource/document/stedelijk-museum-schiedam/H-00002926"/><edm:object rdf:resource="https://api.stedelijkmuseumschiedam.nl/axiellweboai/wwwopac.ashx?command=getcontent&amp;server=images&amp;value=H-00002926.jpg"/><edm:dataProvider>Stedelijk Museum Schiedam</edm:dataProvider><edm:provider>Rijksdienst voor het Cultureel Erfgoed</edm:provider><edm:rights rdf:resource="https://rightsstatements.org/page/InC/1.0/"/><edm:isShownBy rdf:resource="https://api.stedelijkmuseumschiedam.nl/axiellweboai/wwwopac.ashx?command=getcontent&amp;server=images&amp;value=H-00002926.jpg"/></ore:Aggregation><edm:ProvidedCHO rdf:about="http://data.collectienederland.nl/resource/document/stedelijk-museum-schiedam/H-00002926"><dc:creator>onbekend</dc:creator><dc:identifier>H-00002926</dc:identifier><dcterms:created>1700 / 1720</dcterms:created><dcterms:extent>diameter: 9,8 cm</dcterms:extent><dc:title>Schotel met Chinees blauw bloemendecor</dc:title><dc:type>schotel</dc:type><dcterms:extent>hoogte: 1,7 cm</dcterms:extent><dcterms:provenance>Stedelijk Museum Schiedam</dcterms:provenance><dc:date>1700 / 1720</dc:date></edm:ProvidedCHO></rdf:RDF>