<rdf:RDF xmlns:dc="http://purl.org/dc/elements/1.1/" xmlns:edm="http://www.europeana.eu/schemas/edm/" xmlns:nave="http://schemas.delving.eu/nave/terms/" xmlns:ore="http://www.openarchives.org/ore/terms/" xmlns:rdf="http://www.w3.org/1999/02/22-rdf-syntax-ns#"><edm:ProvidedCHO rdf:about="http://data.collectienederland.nl/resource/document/rijksakademie/5064"><dc:title>Constantin, naar Rubens</dc:title><dc:subject>prentenverzameling</dc:subject><dc:format>Breedte 2 65.5 CM</dc:format><dc:subject>kopie</dc:subject><dc:subject>wapen</dc:subject><edm:type>TEXT</edm:type><dc:date>1600</dc:date><dc:relation>-</dc:relation><dc:format>hoogte 39.4 CM</dc:format><dc:language>Nederlands</dc:language><dc:publisher>Rijksakademie van beeldende kunsten</dc:publisher><dc:subject>horse</dc:subject><dc:format>Hoogte 1 48.8 CM</dc:format><dc:identifier>5064</dc:identifier><dc:description>Strijd tussen twee legers. Op de voorgrond, onder het paard van een romein met lauwerkrans op, liggen twee lichamen. Gravure naar P. Rubens, met een tekst in rijm.</dc:description><dc:type>gravure</dc:type><dc:subject>figuren</dc:subject><dc:subject>historie</dc:subject><dc:subject>strijder</dc:subject><dc:source>Rijksakademie van beeldende kunsten</dc:source><dc:subject>animals</dc:subject><dc:creator>Balthasar Moncornet</dc:creator><dc:subject>tekst</dc:subject><dc:date>1668</dc:date><dc:format>breedte 57.1 CM</dc:format></edm:ProvidedCHO><ore:Aggregation rdf:about="http://data.collectienederland.nl/resource/aggregation/rijksakademie/5064"><edm:object rdf:resource="https://rabk.adlibhosting.com/wwwopacx/wwwopac.ashx?command=getcontent&amp;server=images&amp;value=/kerncollectie/5064.jpg"/><edm:dataProvider>Rijksakademie van beeldende kunsten</edm:dataProvider><edm:isShownBy rdf:resource="https://rabk.adlibhosting.com/wwwopacx/wwwopac.ashx?command=getcontent&amp;server=images&amp;value=/kerncollectie/5064.jpg"/><edm:rights rdf:resource="http://rightsstatements.org/page/InC/1.0/?language=nl"/><edm:provider>Rijksdienst voor het Cultureel Erfgoed</edm:provider><edm:aggregatedCHO rdf:resource="http://data.collectienederland.nl/resource/document/rijksakademie/5064"/><edm:isShownAt rdf:resource="http://data.collectienederland.nl/resource/aggregation/rijksakademie/5064"/></ore:Aggregation></rdf:RDF>