<rdf:RDF xmlns:dc="http://purl.org/dc/elements/1.1/" xmlns:edm="http://www.europeana.eu/schemas/edm/" xmlns:nave="http://schemas.delving.eu/nave/terms/" xmlns:ore="http://www.openarchives.org/ore/terms/" xmlns:rdf="http://www.w3.org/1999/02/22-rdf-syntax-ns#"><ore:Aggregation rdf:about="http://data.collectienederland.nl/resource/aggregation/rijksakademie/9485"><edm:isShownAt rdf:resource="http://data.collectienederland.nl/resource/aggregation/rijksakademie/9485"/><edm:aggregatedCHO rdf:resource="http://data.collectienederland.nl/resource/document/rijksakademie/9485"/><edm:object rdf:resource="https://rabk.adlibhosting.com/wwwopacx/wwwopac.ashx?command=getcontent&amp;server=images&amp;value=/kerncollectie/9485.jpg"/><edm:isShownBy rdf:resource="https://rabk.adlibhosting.com/wwwopacx/wwwopac.ashx?command=getcontent&amp;server=images&amp;value=/kerncollectie/9485.jpg"/><edm:rights rdf:resource="http://rightsstatements.org/page/InC/1.0/?language=nl"/><edm:dataProvider>Rijksakademie van beeldende kunsten</edm:dataProvider><edm:provider>Rijksdienst voor het Cultureel Erfgoed</edm:provider></ore:Aggregation><edm:ProvidedCHO rdf:about="http://data.collectienederland.nl/resource/document/rijksakademie/9485"><dc:source>Rijksakademie van beeldende kunsten</dc:source><dc:date>1914</dc:date><dc:format>breedte 48 CM</dc:format><dc:title>Spierstudie</dc:title><edm:type>TEXT</edm:type><dc:language>Nederlands</dc:language><dc:subject>spier</dc:subject><dc:format>hoogte 61.8 CM</dc:format><dc:subject>spiertekening</dc:subject><dc:creator>Annie van Tricht - Fokker</dc:creator><dc:subject>body</dc:subject><dc:identifier>9485</dc:identifier><dc:publisher>Rijksakademie van beeldende kunsten</dc:publisher><dc:subject>anatomie</dc:subject><dc:subject>Prix de Rome</dc:subject><dc:subject>hoofd</dc:subject><dc:description>Spiertekening van een hoofd, profiel naar links. Rechts een klein schetsje.</dc:description><dc:type>tekening</dc:type></edm:ProvidedCHO></rdf:RDF>