<rdf:RDF xmlns:dc="http://purl.org/dc/elements/1.1/" xmlns:dcterms="http://purl.org/dc/terms/" xmlns:edm="http://www.europeana.eu/schemas/edm/" xmlns:nave="http://schemas.delving.eu/nave/terms/" xmlns:ore="http://www.openarchives.org/ore/terms/" xmlns:rdf="http://www.w3.org/1999/02/22-rdf-syntax-ns#"><ore:Aggregation rdf:about="http://data.collectienederland.nl/resource/aggregation/museum-de-fundatie/0000000797"><edm:aggregatedCHO rdf:resource="http://data.collectienederland.nl/resource/document/museum-de-fundatie/0000000797"/><edm:provider>Rijksdienst voor het Cultureel Erfgoed</edm:provider><edm:isShownBy rdf:resource="https://media.delving.org/thumbnail/dcn/museum-de-fundatie/0000000797/2000"/><edm:object rdf:resource="https://media.delving.org/thumbnail/dcn/museum-de-fundatie/0000000797/500"/><edm:rights rdf:resource="https://rightsstatements.org/page/InC/1.0/"/><edm:dataProvider>Museum de Fundatie</edm:dataProvider></ore:Aggregation><edm:ProvidedCHO rdf:about="http://data.collectienederland.nl/resource/document/museum-de-fundatie/0000000797"><edm:type>IMAGE</edm:type><dcterms:extent>14.0 cm</dcterms:extent><dc:creator>Joseph (II) Mendes da Costa</dc:creator><dc:type>kunstnijverheid</dc:type><dc:date>1939</dc:date><dc:title>Maquette grafmonument</dc:title><dcterms:extent>15.5 cm</dcterms:extent><dc:type>keramiek</dc:type><dc:identifier>0000000797</dc:identifier><dc:format>15.5 cm</dc:format><dc:format>3.0 cm</dc:format><dc:format>14.0 cm</dc:format><dcterms:extent>3.0 cm</dcterms:extent><dc:type>sculptuur</dc:type></edm:ProvidedCHO></rdf:RDF>