<rdf:RDF xmlns:dc="http://purl.org/dc/elements/1.1/" xmlns:dcterms="http://purl.org/dc/terms/" xmlns:edm="http://www.europeana.eu/schemas/edm/" xmlns:nave="http://schemas.delving.eu/nave/terms/" xmlns:ore="http://www.openarchives.org/ore/terms/" xmlns:rdf="http://www.w3.org/1999/02/22-rdf-syntax-ns#"><edm:ProvidedCHO rdf:about="http://data.collectienederland.nl/resource/document/museum-de-fundatie/0000002079"><dcterms:isReferencedBy>Samenhang en contrasten : twintigste-eeuwse schilderkunst en sculptuur Hannema-de Stuers Fundatie, Heino / [tekst en samenst. André Kraayenga ; fotogr. Paul Voorham] ; met een voorw. van Wim H. Crouwel</dcterms:isReferencedBy><dcterms:isReferencedBy>Moderne kunst in Nederland : 1900-1914 / A.B. Loosjes-Terpstra</dcterms:isReferencedBy><dcterms:extent>4.5 cm</dcterms:extent><dcterms:extent>75.5 cm</dcterms:extent><dc:format>36.0 cm</dc:format><dc:format>75.5 cm</dc:format><dcterms:isReferencedBy>Meesters van het licht : luministische schilderkunst in Nederland en Duitsland / Carel Blotkamp, Ina Ewers-Schultz, Gerda Wendermann</dcterms:isReferencedBy><dc:creator>Leo Gestel</dc:creator><dcterms:isReferencedBy>Leo Gestel : schilder en tekenaar / Marijke E.Th. Estourgie-Beijer, Eveline Heuves ; m.m.v. Dominique Colen</dcterms:isReferencedBy><dc:format>4.5 cm</dc:format><dcterms:isReferencedBy>Favorieten van Museum de Fundatie</dcterms:isReferencedBy><dc:format>50 cm</dc:format><dc:date>1909</dc:date><dcterms:extent>50 cm</dcterms:extent><dc:format>62.0 cm</dc:format><dc:identifier>0000002079</dc:identifier><dc:type>schilderij</dc:type><dc:title>Liggend naakt</dc:title><dcterms:extent>36.0 cm</dcterms:extent><edm:type>IMAGE</edm:type><dcterms:isReferencedBy>Aufbruch zur Farbe : luministische Malerei in Holland und Deutschland / [teksten: Ina Ewers-Schultz, Gerda Wendermann, Carel Blotkamp...et al.]</dcterms:isReferencedBy><dcterms:extent>62.0 cm</dcterms:extent></edm:ProvidedCHO><ore:Aggregation rdf:about="http://data.collectienederland.nl/resource/aggregation/museum-de-fundatie/0000002079"><edm:object rdf:resource="https://media.delving.org/thumbnail/dcn/museum-de-fundatie/0000002079/500"/><edm:provider>Rijksdienst voor het Cultureel Erfgoed</edm:provider><edm:isShownBy rdf:resource="https://media.delving.org/thumbnail/dcn/museum-de-fundatie/0000002079/2000"/><edm:rights rdf:resource="https://rightsstatements.org/page/InC/1.0/"/><edm:aggregatedCHO rdf:resource="http://data.collectienederland.nl/resource/document/museum-de-fundatie/0000002079"/><edm:dataProvider>Museum de Fundatie</edm:dataProvider></ore:Aggregation></rdf:RDF>